globus_compute_sdk/__init__.py
globus_compute_sdk/py.typed
globus_compute_sdk/version.py
globus_compute_sdk/errors/__init__.py
globus_compute_sdk/errors/error_types.py
globus_compute_sdk/sdk/__init__.py
globus_compute_sdk/sdk/_environments.py
globus_compute_sdk/sdk/batch.py
globus_compute_sdk/sdk/client.py
globus_compute_sdk/sdk/compute_dir.py
globus_compute_sdk/sdk/container_spec.py
globus_compute_sdk/sdk/diagnostic.py
globus_compute_sdk/sdk/executor.py
globus_compute_sdk/sdk/hardware_report.py
globus_compute_sdk/sdk/mpi_function.py
globus_compute_sdk/sdk/shell_function.py
globus_compute_sdk/sdk/web_client.py
globus_compute_sdk/sdk/asynchronous/__init__.py
globus_compute_sdk/sdk/asynchronous/compute_future.py
globus_compute_sdk/sdk/asynchronous/compute_task.py
globus_compute_sdk/sdk/auth/__init__.py
globus_compute_sdk/sdk/auth/auth_client.py
globus_compute_sdk/sdk/auth/client_login.py
globus_compute_sdk/sdk/auth/globus_app.py
globus_compute_sdk/sdk/auth/scopes.py
globus_compute_sdk/sdk/auth/token_storage.py
globus_compute_sdk/sdk/auth/whoami.py
globus_compute_sdk/sdk/login_manager/__init__.py
globus_compute_sdk/sdk/login_manager/authorizer_login_manager.py
globus_compute_sdk/sdk/login_manager/client_login.py
globus_compute_sdk/sdk/login_manager/globus_auth.py
globus_compute_sdk/sdk/login_manager/login_flow.py
globus_compute_sdk/sdk/login_manager/manager.py
globus_compute_sdk/sdk/login_manager/protocol.py
globus_compute_sdk/sdk/login_manager/tokenstore.py
globus_compute_sdk/sdk/utils/__init__.py
globus_compute_sdk/sdk/utils/gare.py
globus_compute_sdk/sdk/utils/printing.py
globus_compute_sdk/sdk/utils/sample_function.py
globus_compute_sdk/sdk/utils/uuid_like.py
globus_compute_sdk/serialize/__init__.py
globus_compute_sdk/serialize/base.py
globus_compute_sdk/serialize/concretes.py
globus_compute_sdk/serialize/facade.py
globus_compute_sdk/serialize/utils.py
globus_compute_sdk-4.1.0.dist-info/licenses/LICENSE
globus_compute_sdk-4.1.0.dist-info/METADATA
globus_compute_sdk-4.1.0.dist-info/WHEEL
globus_compute_sdk-4.1.0.dist-info/entry_points.txt
globus_compute_sdk-4.1.0.dist-info/top_level.txt
globus_compute_sdk-4.1.0.dist-info/RECORD
